CHANGELOG.rst
LICENSE.txt
MANIFEST.in
README.rst
setup.cfg
setup.py
config_logger/__init__.py
config_logger/filters.py
config_logger/logger.py
config_logger.egg-info/PKG-INFO
config_logger.egg-info/SOURCES.txt
config_logger.egg-info/dependency_links.txt
config_logger.egg-info/requires.txt
config_logger.egg-info/top_level.txt
tests/__init__.py
tests/filters_test.py
tests/logger_test.py